nvtabular_cpp.cpython-311-x86_64-linux-musl.so
nvtabular-23.8.0.dist-info/RECORD
nvtabular-23.8.0.dist-info/WHEEL
nvtabular-23.8.0.dist-info/LICENSE
nvtabular-23.8.0.dist-info/METADATA
nvtabular-23.8.0.dist-info/top_level.txt
nvtabular/_version.py
nvtabular/__init__.py
nvtabular/graph.py
nvtabular/worker.py
nvtabular/io.py
nvtabular/dispatch.py
nvtabular/utils.py
nvtabular/ops/value_counts.py
nvtabular/ops/join_external.py
nvtabular/ops/operator.py
nvtabular/ops/bucketize.py
nvtabular/ops/normalize.py
nvtabular/ops/fill.py
nvtabular/ops/__init__.py
nvtabular/ops/dropna.py
nvtabular/ops/categorify.py
nvtabular/ops/hashed_cross.py
nvtabular/ops/list_slice.py
nvtabular/ops/logop.py
nvtabular/ops/lambdaop.py
nvtabular/ops/join_groupby.py
nvtabular/ops/target_encoding.py
nvtabular/ops/data_stats.py
nvtabular/ops/drop_low_cardinality.py
nvtabular/ops/groupby.py
nvtabular/ops/rename.py
nvtabular/ops/filter.py
nvtabular/ops/clip.py
nvtabular/ops/hash_bucket.py
nvtabular/ops/stat_operator.py
nvtabular/ops/column_similarity.py
nvtabular/ops/add_metadata.py
nvtabular/ops/reduce_dtype_size.py
nvtabular/ops/moments.py
nvtabular/ops/difference_lag.py
nvtabular/tools/dataset_inspector.py
nvtabular/tools/__init__.py
nvtabular/tools/data_gen.py
nvtabular/tools/inspector_script.py
nvtabular/workflow/workflow.py
nvtabular/workflow/node.py
nvtabular/workflow/__init__.py
nvtabular/framework_utils/__init__.py
nvtabular/framework_utils/torch/__init__.py
nvtabular/framework_utils/torch/models.py
nvtabular/framework_utils/torch/utils.py
nvtabular/framework_utils/torch/layers/__init__.py
nvtabular/framework_utils/torch/layers/embeddings.py
nvtabular/framework_utils/tensorflow/__init__.py
nvtabular/framework_utils/tensorflow/feature_column_utils.py
nvtabular/framework_utils/tensorflow/tfrecords_to_parquet.py
nvtabular/framework_utils/tensorflow/layers/__init__.py
nvtabular/framework_utils/tensorflow/layers/embedding.py
nvtabular/framework_utils/tensorflow/layers/outer_product.py
nvtabular/framework_utils/tensorflow/layers/interaction.py
nvtabular/inference/__init__.py
nvtabular/loader/backend.py
