Metadata-Version: 2.1
Name: nvtabular
Version: 23.8.0
Home-page: https://github.com/NVIDIA-Merlin/NVTabular
Author: NVIDIA Corporation
License: Apache 2.0
Classifier: Development Status :: 4 - Beta
Classifier: Programming Language :: Python :: 3
Classifier: Programming Language :: Python :: 3.8
Classifier: Programming Language :: Python :: 3.9
Classifier: Programming Language :: Python :: 3.10
Classifier: Programming Language :: Python :: 3 :: Only
Classifier: Intended Audience :: Developers
Classifier: License :: OSI Approved :: Apache Software License
Classifier: Topic :: Software Development :: Libraries
Classifier: Topic :: Scientific/Engineering
Requires-Python: >=3.8
License-File: LICENSE
Requires-Dist: merlin-core >=23.4.0
Requires-Dist: merlin-dataloader >=23.4.0
Requires-Dist: scipy
Provides-Extra: gpu
Requires-Dist: cudf-cu11 ; extra == 'gpu'
Requires-Dist: dask-cudf-cu11 ; extra == 'gpu'
Requires-Dist: cupy-cuda11x ; extra == 'gpu'
